<?xml version="1.0" encoding="UTF-8"?>
<page view-id="#{menuItemConstant.yoneticiDegistir}" xmlns="http://jboss.com/products/seam/pages" xmlns:xsi="http://www.w3.org/2001/XMLSchema-instance" xsi:schemaLocation="http://jboss.com/products/seam/pages http://jboss.com/products/seam/pages-2.1.xsd">
	<restrict>#{userHome.hasPermission('yoneticiDegistir','view')}</restrict>
	<rewrite pattern="/yoneticiDegistir" />
	<action execute="#{yoneticiDegistirHome.sayfaGirisAction}" on-postback="false" />
	<navigation>
		<rule if-outcome="yoneticiDegistir">
			<redirect view-id="#{menuItemConstant.yoneticiDegistir}" />
		</rule>
		<rule if-outcome="home">
			<redirect view-id="#{menuItemConstant.home}" />
		</rule>		
	</navigation>
</page>
